{
  "kind": "collectionType",
  "collectionName": "shoe_variations",
  "info": {
    "singularName": "shoe-variation",
    "pluralName": "shoe-variations",
    "displayName": "Shoe Variation",
    "description": ""
  },
  "options": {
    "draftAndPublish": true
  },
  "pluginOptions": {},
  "attributes": {
    "productImages": {
      "type": "media",
      "multiple": true,
      "required": false,
      "allowedTypes": [
        "images",
        "files",
        "videos",
        "audios"
      ]
    },
    "shoe": {
      "type": "relation",
      "relation": "oneToOne",
      "target": "api::shoe.shoe"
    },
    "color": {
      "type": "relation",
      "relation": "oneToOne",
      "target": "api::color.color"
    }
  }
}
